tests/__init__.py
tests/test_covid_dashboard.py
tests/test_covid_data_handler.py
tests/test_news_data_handling.py
Covid_dashboard_pkg_rt539-1.0.1.dist-info/LICENSE.txt
Covid_dashboard_pkg_rt539-1.0.1.dist-info/METADATA
Covid_dashboard_pkg_rt539-1.0.1.dist-info/WHEEL
Covid_dashboard_pkg_rt539-1.0.1.dist-info/top_level.txt
Covid_dashboard_pkg_rt539-1.0.1.dist-info/RECORD
