Metadata-Version: 2.1
Name: Covid-dashboard-pkg-rt539
Version: 1.0.1
Summary: Lightweight covid dashboard
Home-page: https://github.com/Toffoh/Covid-Dashboard
Author: Ryan Toffoletti
Author-email: rt539@exeter.ac.uk
License: UNKNOWN
Platform: UNKNOWN
Classifier: Programming Language :: Python :: 3
Classifier: License :: OSI Approved :: MIT License
Classifier: Operating System :: OS Independent
Requires-Python: >=3.10
License-File: LICENSE.txt
Requires-Dist: Flask
Requires-Dist: requests
Requires-Dist: pytest
Requires-Dist: sched
